gap_statistic/__init__.py
gap_statistic/optimalK.py
gap_stat-2.0.2.dist-info/LICENSE-MIT
gap_stat-2.0.2.dist-info/METADATA
gap_stat-2.0.2.dist-info/WHEEL
gap_stat-2.0.2.dist-info/top_level.txt
gap_stat-2.0.2.dist-info/RECORD
