Metadata-Version: 2.1
Name: gap-stat
Version: 2.0.2
Summary: Python implementation of the gap statistic with optional Rust optimizations.
Home-page: https://github.com/milesgranger/gap_statistic
Author: Miles Granger
Author-email: miles59923@gmail.com
Maintainer: Miles Granger
Maintainer-email: miles59923@gmail.com
License: MIT
Keywords: kmeans unsupervised learning machine-learning clustering
Classifier: Development Status :: 5 - Production/Stable
Classifier: Intended Audience :: Developers
Classifier: Intended Audience :: Financial and Insurance Industry
Classifier: Intended Audience :: Information Technology
Classifier: Intended Audience :: Science/Research
Classifier: Programming Language :: Python
Classifier: Programming Language :: Python :: 3.5
Classifier: Programming Language :: Python :: 3.6
Classifier: Programming Language :: Python :: 3 :: Only
Classifier: Programming Language :: Rust
Classifier: Operating System :: Microsoft :: Windows
Classifier: Operating System :: POSIX
Classifier: Operating System :: Unix
Classifier: Operating System :: MacOS :: MacOS X
License-File: LICENSE-MIT
Requires-Dist: numpy
Requires-Dist: pandas
Requires-Dist: scipy
Provides-Extra: rust
Requires-Dist: gapstat-rs ; extra == 'rust'
